paperparser/__init__.py
paperparser/abstract_parser.py
paperparser/bibtex_parser.py
paperparser/console.py
paperparser/page.py
paperparser-0.2.2.dist-info/entry_points.txt
paperparser-0.2.2.dist-info/LICENSE
paperparser-0.2.2.dist-info/WHEEL
paperparser-0.2.2.dist-info/METADATA
paperparser-0.2.2.dist-info/RECORD
