Metadata-Version: 2.1
Name: paperparser
Version: 0.2.2
Summary: A tool for parsing academic papers
Home-page: https://gitlab.com/winderresearch/tools/PaperParser
License: MIT
Author: Phil Winder
Author-email: phil@WinderResearch.com
Requires-Python: >=3.7,<4.0
Classifier: License :: OSI Approved :: MIT License
Classifier: Programming Language :: Python :: 3
Classifier: Programming Language :: Python :: 3.7
Classifier: Programming Language :: Python :: 3.8
Requires-Dist: arxiv2bib (>=1.0.8,<2.0.0)
Requires-Dist: click (>=7.0,<8.0)
Requires-Dist: desert (>=2020.1.6,<2021.0.0)
Requires-Dist: importlib-metadata (>=1.5.0,<2.0.0); python_version < "3.8"
Requires-Dist: marshmallow (>=3.3.0,<4.0.0)
Requires-Dist: pybtex (>=0.22.2,<0.23.0)
Requires-Dist: pyquery (>=1.4.1,<2.0.0)
Requires-Dist: requests (>=2.22.0,<3.0.0)
Project-URL: Documentation, https://gitlab.com/winderresearch/tools/PaperParser
Project-URL: Repository, https://gitlab.com/winderresearch/tools/PaperParser
